[
  {
    "scrollPercent": 0,
    "diffs": [
      {
        "browserA": "chromium",
        "browserB": "firefox",
        "diffPercent": 21.18,
        "diffImagePath": "C:\\Users\\theoo\\OneDrive\\Bureau\\SOTY\\event-horizon\\scripts\\soty-upgrader\\reports\\cycle-10\\cross-browser\\diffs\\diff-chromium-firefox-000.png"
      },
      {
        "browserA": "chromium",
        "browserB": "webkit",
        "diffPercent": 23.54,
        "diffImagePath": "C:\\Users\\theoo\\OneDrive\\Bureau\\SOTY\\event-horizon\\scripts\\soty-upgrader\\reports\\cycle-10\\cross-browser\\diffs\\diff-chromium-webkit-000.png"
      },
      {
        "browserA": "firefox",
        "browserB": "webkit",
        "diffPercent": 22.73,
        "diffImagePath": "C:\\Users\\theoo\\OneDrive\\Bureau\\SOTY\\event-horizon\\scripts\\soty-upgrader\\reports\\cycle-10\\cross-browser\\diffs\\diff-firefox-webkit-000.png"
      }
    ]
  },
  {
    "scrollPercent": 0.1,
    "diffs": [
      {
        "browserA": "chromium",
        "browserB": "firefox",
        "diffPercent": 9.6,
        "diffImagePath": "C:\\Users\\theoo\\OneDrive\\Bureau\\SOTY\\event-horizon\\scripts\\soty-upgrader\\reports\\cycle-10\\cross-browser\\diffs\\diff-chromium-firefox-010.png"
      },
      {
        "browserA": "chromium",
        "browserB": "webkit",
        "diffPercent": 16.72,
        "diffImagePath": "C:\\Users\\theoo\\OneDrive\\Bureau\\SOTY\\event-horizon\\scripts\\soty-upgrader\\reports\\cycle-10\\cross-browser\\diffs\\diff-chromium-webkit-010.png"
      },
      {
        "browserA": "firefox",
        "browserB": "webkit",
        "diffPercent": 13.25,
        "diffImagePath": "C:\\Users\\theoo\\OneDrive\\Bureau\\SOTY\\event-horizon\\scripts\\soty-upgrader\\reports\\cycle-10\\cross-browser\\diffs\\diff-firefox-webkit-010.png"
      }
    ]
  },
  {
    "scrollPercent": 0.25,
    "diffs": [
      {
        "browserA": "chromium",
        "browserB": "firefox",
        "diffPercent": 16.08,
        "diffImagePath": "C:\\Users\\theoo\\OneDrive\\Bureau\\SOTY\\event-horizon\\scripts\\soty-upgrader\\reports\\cycle-10\\cross-browser\\diffs\\diff-chromium-firefox-025.png"
      },
      {
        "browserA": "chromium",
        "browserB": "webkit",
        "diffPercent": 19.91,
        "diffImagePath": "C:\\Users\\theoo\\OneDrive\\Bureau\\SOTY\\event-horizon\\scripts\\soty-upgrader\\reports\\cycle-10\\cross-browser\\diffs\\diff-chromium-webkit-025.png"
      },
      {
        "browserA": "firefox",
        "browserB": "webkit",
        "diffPercent": 5.39,
        "diffImagePath": "C:\\Users\\theoo\\OneDrive\\Bureau\\SOTY\\event-horizon\\scripts\\soty-upgrader\\reports\\cycle-10\\cross-browser\\diffs\\diff-firefox-webkit-025.png"
      }
    ]
  },
  {
    "scrollPercent": 0.4,
    "diffs": [
      {
        "browserA": "chromium",
        "browserB": "firefox",
        "diffPercent": 21.43,
        "diffImagePath": "C:\\Users\\theoo\\OneDrive\\Bureau\\SOTY\\event-horizon\\scripts\\soty-upgrader\\reports\\cycle-10\\cross-browser\\diffs\\diff-chromium-firefox-040.png"
      },
      {
        "browserA": "chromium",
        "browserB": "webkit",
        "diffPercent": 23.19,
        "diffImagePath": "C:\\Users\\theoo\\OneDrive\\Bureau\\SOTY\\event-horizon\\scripts\\soty-upgrader\\reports\\cycle-10\\cross-browser\\diffs\\diff-chromium-webkit-040.png"
      },
      {
        "browserA": "firefox",
        "browserB": "webkit",
        "diffPercent": 18.95,
        "diffImagePath": "C:\\Users\\theoo\\OneDrive\\Bureau\\SOTY\\event-horizon\\scripts\\soty-upgrader\\reports\\cycle-10\\cross-browser\\diffs\\diff-firefox-webkit-040.png"
      }
    ]
  },
  {
    "scrollPercent": 0.5,
    "diffs": [
      {
        "browserA": "chromium",
        "browserB": "firefox",
        "diffPercent": 22.36,
        "diffImagePath": "C:\\Users\\theoo\\OneDrive\\Bureau\\SOTY\\event-horizon\\scripts\\soty-upgrader\\reports\\cycle-10\\cross-browser\\diffs\\diff-chromium-firefox-050.png"
      },
      {
        "browserA": "chromium",
        "browserB": "webkit",
        "diffPercent": 20.66,
        "diffImagePath": "C:\\Users\\theoo\\OneDrive\\Bureau\\SOTY\\event-horizon\\scripts\\soty-upgrader\\reports\\cycle-10\\cross-browser\\diffs\\diff-chromium-webkit-050.png"
      },
      {
        "browserA": "firefox",
        "browserB": "webkit",
        "diffPercent": 20.17,
        "diffImagePath": "C:\\Users\\theoo\\OneDrive\\Bureau\\SOTY\\event-horizon\\scripts\\soty-upgrader\\reports\\cycle-10\\cross-browser\\diffs\\diff-firefox-webkit-050.png"
      }
    ]
  },
  {
    "scrollPercent": 0.65,
    "diffs": [
      {
        "browserA": "chromium",
        "browserB": "firefox",
        "diffPercent": 33.22,
        "diffImagePath": "C:\\Users\\theoo\\OneDrive\\Bureau\\SOTY\\event-horizon\\scripts\\soty-upgrader\\reports\\cycle-10\\cross-browser\\diffs\\diff-chromium-firefox-065.png"
      },
      {
        "browserA": "chromium",
        "browserB": "webkit",
        "diffPercent": 56.69,
        "diffImagePath": "C:\\Users\\theoo\\OneDrive\\Bureau\\SOTY\\event-horizon\\scripts\\soty-upgrader\\reports\\cycle-10\\cross-browser\\diffs\\diff-chromium-webkit-065.png"
      },
      {
        "browserA": "firefox",
        "browserB": "webkit",
        "diffPercent": 78.81,
        "diffImagePath": "C:\\Users\\theoo\\OneDrive\\Bureau\\SOTY\\event-horizon\\scripts\\soty-upgrader\\reports\\cycle-10\\cross-browser\\diffs\\diff-firefox-webkit-065.png"
      }
    ]
  },
  {
    "scrollPercent": 0.75,
    "diffs": [
      {
        "browserA": "chromium",
        "browserB": "firefox",
        "diffPercent": 2.74,
        "diffImagePath": "C:\\Users\\theoo\\OneDrive\\Bureau\\SOTY\\event-horizon\\scripts\\soty-upgrader\\reports\\cycle-10\\cross-browser\\diffs\\diff-chromium-firefox-075.png"
      },
      {
        "browserA": "chromium",
        "browserB": "webkit",
        "diffPercent": 65.09,
        "diffImagePath": "C:\\Users\\theoo\\OneDrive\\Bureau\\SOTY\\event-horizon\\scripts\\soty-upgrader\\reports\\cycle-10\\cross-browser\\diffs\\diff-chromium-webkit-075.png"
      },
      {
        "browserA": "firefox",
        "browserB": "webkit",
        "diffPercent": 60.86,
        "diffImagePath": "C:\\Users\\theoo\\OneDrive\\Bureau\\SOTY\\event-horizon\\scripts\\soty-upgrader\\reports\\cycle-10\\cross-browser\\diffs\\diff-firefox-webkit-075.png"
      }
    ]
  },
  {
    "scrollPercent": 0.9,
    "diffs": [
      {
        "browserA": "chromium",
        "browserB": "firefox",
        "diffPercent": 16.04,
        "diffImagePath": "C:\\Users\\theoo\\OneDrive\\Bureau\\SOTY\\event-horizon\\scripts\\soty-upgrader\\reports\\cycle-10\\cross-browser\\diffs\\diff-chromium-firefox-090.png"
      },
      {
        "browserA": "chromium",
        "browserB": "webkit",
        "diffPercent": 3.7,
        "diffImagePath": "C:\\Users\\theoo\\OneDrive\\Bureau\\SOTY\\event-horizon\\scripts\\soty-upgrader\\reports\\cycle-10\\cross-browser\\diffs\\diff-chromium-webkit-090.png"
      },
      {
        "browserA": "firefox",
        "browserB": "webkit",
        "diffPercent": 13.44,
        "diffImagePath": "C:\\Users\\theoo\\OneDrive\\Bureau\\SOTY\\event-horizon\\scripts\\soty-upgrader\\reports\\cycle-10\\cross-browser\\diffs\\diff-firefox-webkit-090.png"
      }
    ]
  },
  {
    "scrollPercent": 1,
    "diffs": [
      {
        "browserA": "chromium",
        "browserB": "firefox",
        "diffPercent": 100,
        "diffImagePath": "C:\\Users\\theoo\\OneDrive\\Bureau\\SOTY\\event-horizon\\scripts\\soty-upgrader\\reports\\cycle-10\\cross-browser\\diffs\\diff-chromium-firefox-100.png"
      },
      {
        "browserA": "chromium",
        "browserB": "webkit",
        "diffPercent": 1.19,
        "diffImagePath": "C:\\Users\\theoo\\OneDrive\\Bureau\\SOTY\\event-horizon\\scripts\\soty-upgrader\\reports\\cycle-10\\cross-browser\\diffs\\diff-chromium-webkit-100.png"
      },
      {
        "browserA": "firefox",
        "browserB": "webkit",
        "diffPercent": 99.7,
        "diffImagePath": "C:\\Users\\theoo\\OneDrive\\Bureau\\SOTY\\event-horizon\\scripts\\soty-upgrader\\reports\\cycle-10\\cross-browser\\diffs\\diff-firefox-webkit-100.png"
      }
    ]
  }
]